liveimport/__init__.py
liveimport/_core.py
liveimport/_debug.py
liveimport/_nbi.py
liveimport/_workspace.py
liveimport-1.2.4.dist-info/licenses/LICENSE
liveimport-1.2.4.dist-info/METADATA
liveimport-1.2.4.dist-info/WHEEL
liveimport-1.2.4.dist-info/top_level.txt
liveimport-1.2.4.dist-info/RECORD
