Metadata-Version: 2.4
Name: liveimport
Version: 1.2.4
Summary: Automatically reload modified Python modules in notebooks and scripts.
Author: Edward Screven
License-Expression: MIT
Project-URL: Homepage, https://github.com/escreven/liveimport
Project-URL: Repository, https://github.com/escreven/liveimport
Project-URL: Documentation, https://liveimport.readthedocs.io
Project-URL: Issues, https://github.com/escreven/liveimport/issues
Keywords: notebook,jupyter,ipython,import,reload,autoreload
Classifier: Operating System :: OS Independent
Classifier: Framework :: IPython
Classifier: Framework :: Jupyter
Classifier: Programming Language :: Python :: 3
Classifier: Programming Language :: Python :: 3.10
Classifier: Programming Language :: Python :: 3.11
Classifier: Programming Language :: Python :: 3.12
Classifier: Programming Language :: Python :: 3.13
Classifier: Programming Language :: Python :: 3.14
Classifier: Topic :: Software Development :: Libraries :: Python Modules
Requires-Python: >=3.10
License-File: LICENSE
Requires-Dist: IPython>=7.23.1
Dynamic: license-file
